{
  "session_id": "migration_202507_140757_b5827929",
  "organization": "Long Focus Capital Management, LLC",
  "timestamp": "2025-09-07T14:10:05.495267",
  "total_processed": 72,
  "successful": 72,
  "failed": 0,
  "results": [
    {
      "asset_id": "55852087",
      "asset_name": "No office and Wireless no wireless",
      "action": "created",
      "success": true,
      "servicenow_sys_id": "a7a8a5d2477b66103c5e88f4116d4311",
      "error_message": null
    },
    {
      "asset_id": "55845684",
      "asset_name": "No Active directory environment n/a",
      "action": "created",
      "success": true,
      "servicenow_sys_id": "efa865d2477b66103c5e88f4116d43b5",
      "error_message": null
    },
    {
      "asset_id": "55666855",
      "asset_name": "Bloomberg",
      "action": "created",
      "success": true,
      "servicenow_sys_id": "afa8a5d2477b66103c5e88f4116d4319",
      "error_message": null
    },
    {
      "asset_id": "55573231",
      "asset_name": "Other",
      "action": "created",
      "success": true,
      "servicenow_sys_id": "27a865d2477b66103c5e88f4116d43f4",
      "error_message": null
    },
    {
      "asset_id": "55667221",
      "asset_name": "Neovest",
      "action": "created",
      "success": true,
      "servicenow_sys_id": "c4b8a5d2477b66103c5e88f4116d43a7",
      "error_message": null
    },
    {
      "asset_id": "55667368",
      "asset_name": "TradeStation",
      "action": "created",
      "success": true,
      "servicenow_sys_id": "8cb8a5d2477b66103c5e88f4116d439f",
      "error_message": null
    },
    {
      "asset_id": "55670098",
      "asset_name": "Microsoft Teams",
      "action": "created",
      "success": true,
      "servicenow_sys_id": "04b8a5d2477b66103c5e88f4116d43c9",
      "error_message": null
    },
    {
      "asset_id": "55670298",
      "asset_name": "\u2022\tQuickbooks",
      "action": "created",
      "success": true,
      "servicenow_sys_id": "4cb8a5d2477b66103c5e88f4116d43f9",
      "error_message": null
    },
    {
      "asset_id": "55670424",
      "asset_name": "Trader Workstation (Interactive Brokers trading)",
      "action": "created",
      "success": true,
      "servicenow_sys_id": "90b8e5d2477b66103c5e88f4116d4356",
      "error_message": null
    },
    {
      "asset_id": "56777418",
      "asset_name": "SentinelOne",
      "action": "created",
      "success": true,
      "servicenow_sys_id": "98b8e5d2477b66103c5e88f4116d434c",
      "error_message": null
    },
    {
      "asset_id": "58286476",
      "asset_name": "Global Relay",
      "action": "created",
      "success": true,
      "servicenow_sys_id": "a0b8e5d2477b66103c5e88f4116d438d",
      "error_message": null
    },
    {
      "asset_id": "58286496",
      "asset_name": "Mimecast",
      "action": "created",
      "success": true,
      "servicenow_sys_id": "e8b8e5d2477b66103c5e88f4116d4393",
      "error_message": null
    },
    {
      "asset_id": "55569442",
      "asset_name": "Microsoft 365",
      "action": "created",
      "success": true,
      "servicenow_sys_id": "24b8e5d2477b66103c5e88f4116d43b6",
      "error_message": null
    },
    {
      "asset_id": "55667712",
      "asset_name": "\uf0a7\tSynology NAS at John Helmers\u2019 home office in Greenville, SC (Synology DS1618+)",
      "action": "created",
      "success": true,
      "servicenow_sys_id": "34b829d2477b66103c5e88f4116d4311",
      "error_message": null
    },
    {
      "asset_id": "55852154",
      "asset_name": "No Circuit WFH",
      "action": "created",
      "success": true,
      "servicenow_sys_id": "4db829d2477b66103c5e88f4116d4373",
      "error_message": null
    },
    {
      "asset_id": "55845206",
      "asset_name": "No Lan Environment",
      "action": "created",
      "success": true,
      "servicenow_sys_id": "05b829d2477b66103c5e88f4116d437b",
      "error_message": null
    },
    {
      "asset_id": "55880175",
      "asset_name": "no remote access technology",
      "action": "created",
      "success": true,
      "servicenow_sys_id": "c9b829d2477b66103c5e88f4116d4389",
      "error_message": null
    },
    {
      "asset_id": "55573227",
      "asset_name": "Vonage",
      "action": "created",
      "success": true,
      "servicenow_sys_id": "05b829d2477b66103c5e88f4116d43f0",
      "error_message": null
    },
    {
      "asset_id": "55667379",
      "asset_name": "Microsoft Team",
      "action": "created",
      "success": true,
      "servicenow_sys_id": "15b869d2477b66103c5e88f4116d4355",
      "error_message": null
    },
    {
      "asset_id": "55667441",
      "asset_name": "Microsoft",
      "action": "created",
      "success": true,
      "servicenow_sys_id": "2db869d2477b66103c5e88f4116d4367",
      "error_message": null
    },
    {
      "asset_id": "55667449",
      "asset_name": "Neovest (JP Morgan trading)",
      "action": "created",
      "success": true,
      "servicenow_sys_id": "e1b869d2477b66103c5e88f4116d437e",
      "error_message": null
    },
    {
      "asset_id": "55667497",
      "asset_name": "TradeStation (charting only)",
      "action": "created",
      "success": true,
      "servicenow_sys_id": "fdb869d2477b66103c5e88f4116d43e1",
      "error_message": null
    },
    {
      "asset_id": "55667506",
      "asset_name": "Bloomberg",
      "action": "created",
      "success": true,
      "servicenow_sys_id": "75b8a9d2477b66103c5e88f4116d4312",
      "error_message": null
    },
    {
      "asset_id": "55667514",
      "asset_name": "Quickbooks",
      "action": "created",
      "success": true,
      "servicenow_sys_id": "06b8a9d2477b66103c5e88f4116d4344",
      "error_message": null
    },
    {
      "asset_id": "55667615",
      "asset_name": "Synology",
      "action": "created",
      "success": true,
      "servicenow_sys_id": "ceb8a9d2477b66103c5e88f4116d4351",
      "error_message": null
    },
    {
      "asset_id": "55667777",
      "asset_name": "Godaddy",
      "action": "created",
      "success": true,
      "servicenow_sys_id": "1eb8a9d2477b66103c5e88f4116d43b2",
      "error_message": null
    },
    {
      "asset_id": "55879399",
      "asset_name": "n/a vendor",
      "action": "created",
      "success": true,
      "servicenow_sys_id": "d2b8a9d2477b66103c5e88f4116d43c1",
      "error_message": null
    },
    {
      "asset_id": "56763249",
      "asset_name": "SentinelOne",
      "action": "created",
      "success": true,
      "servicenow_sys_id": "2eb8e9d2477b66103c5e88f4116d439f",
      "error_message": null
    },
    {
      "asset_id": "58286573",
      "asset_name": "Mimecast",
      "action": "created",
      "success": true,
      "servicenow_sys_id": "e6b8e9d2477b66103c5e88f4116d43a6",
      "error_message": null
    },
    {
      "asset_id": "58286594",
      "asset_name": "Global Relay",
      "action": "created",
      "success": true,
      "servicenow_sys_id": "3ab8e9d2477b66103c5e88f4116d43f1",
      "error_message": null
    },
    {
      "asset_id": "55913559",
      "asset_name": "Other license is manage by app champion for LOB apps",
      "action": "created",
      "success": true,
      "servicenow_sys_id": "72b82dd2477b66103c5e88f4116d4316",
      "error_message": null
    },
    {
      "asset_id": "56765475",
      "asset_name": "Sentinel One 9/0",
      "action": "created",
      "success": true,
      "servicenow_sys_id": "8fb82dd2477b66103c5e88f4116d43c7",
      "error_message": null
    },
    {
      "asset_id": "76426362",
      "asset_name": "Microsoft Long Focus Capital Mgmt Copilot - Action Needed Procurement to invoice for renewa 9/11/26",
      "action": "created",
      "success": true,
      "servicenow_sys_id": "87b82dd2477b66103c5e88f4116d439f",
      "error_message": null
    },
    {
      "asset_id": "55879430",
      "asset_name": "Security",
      "action": "created",
      "success": true,
      "servicenow_sys_id": "53b86dd2477b66103c5e88f4116d4314",
      "error_message": null
    },
    {
      "asset_id": "55909883",
      "asset_name": "Other Files",
      "action": "created",
      "success": true,
      "servicenow_sys_id": "27b86dd2477b66103c5e88f4116d435b",
      "error_message": null
    },
    {
      "asset_id": "55913572",
      "asset_name": "Printing",
      "action": "created",
      "success": true,
      "servicenow_sys_id": "23b86dd2477b66103c5e88f4116d436c",
      "error_message": null
    },
    {
      "asset_id": "55845179",
      "asset_name": "Non Virtualize Environment",
      "action": "created",
      "success": true,
      "servicenow_sys_id": "2fb86dd2477b66103c5e88f4116d439e",
      "error_message": null
    },
    {
      "asset_id": "49225054",
      "asset_name": "Mimecast Directory Synchronization",
      "action": "skipped",
      "success": true,
      "servicenow_sys_id": null,
      "error_message": "Enhanced exclusion: not moving config type"
    },
    {
      "asset_id": "48324588",
      "asset_name": "Synology NAS at John Helmers\u2019 home office (Synology DS1618+)",
      "action": "created",
      "success": true,
      "servicenow_sys_id": "c4c86dd2477b66103c5e88f4116d43d0",
      "error_message": null
    },
    {
      "asset_id": "1182513",
      "asset_name": "lfcap.com",
      "action": "created",
      "success": true,
      "servicenow_sys_id": "98c86dd2477b66103c5e88f4116d43d6",
      "error_message": null
    },
    {
      "asset_id": "10839657",
      "asset_name": "Default Unplanned Outage Process",
      "action": "created",
      "success": true,
      "servicenow_sys_id": "71c8edd2477b66103c5e88f4116d432a",
      "error_message": null
    },
    {
      "asset_id": "10839658",
      "asset_name": "Standard System Specs Sheet - [Long Focus Capital]",
      "action": "created",
      "success": true,
      "servicenow_sys_id": "dec8edd2477b66103c5e88f4116d43a0",
      "error_message": null
    },
    {
      "asset_id": "10839661",
      "asset_name": "User Offboarding Guide - Long Focus Capital",
      "action": "created",
      "success": true,
      "servicenow_sys_id": "3ac82116477b66103c5e88f4116d4342",
      "error_message": null
    },
    {
      "asset_id": "10839662",
      "asset_name": "New User Onboarding Guide - Long Focus Capital",
      "action": "created",
      "success": true,
      "servicenow_sys_id": "07c82116477b66103c5e88f4116d4376",
      "error_message": null
    },
    {
      "asset_id": "13558254",
      "asset_name": "Windows Setup Guide - Long Focus Capital",
      "action": "created",
      "success": true,
      "servicenow_sys_id": "dfc82116477b66103c5e88f4116d43c7",
      "error_message": null
    },
    {
      "asset_id": "14875253",
      "asset_name": "Microsoft Cloud (3).zip",
      "action": "created",
      "success": true,
      "servicenow_sys_id": "67c82116477b66103c5e88f4116d43e5",
      "error_message": null
    },
    {
      "asset_id": "10897786",
      "asset_name": "Long Focus Capital - IKO Doc-REDACTED.docx",
      "action": "created",
      "success": true,
      "servicenow_sys_id": "acd86116477b66103c5e88f4116d43be",
      "error_message": null
    },
    {
      "asset_id": "10872898",
      "asset_name": "Long Focus Capital_Contacts 20220829.xlsx",
      "action": "created",
      "success": true,
      "servicenow_sys_id": "89d8a116477b66103c5e88f4116d430d",
      "error_message": null
    },
    {
      "asset_id": "10872899",
      "asset_name": "Long Focus - Onboarding_Doc 20220829.docx",
      "action": "created",
      "success": true,
      "servicenow_sys_id": "99d8a116477b66103c5e88f4116d4368",
      "error_message": null
    },
    {
      "asset_id": "11537055",
      "asset_name": "LongFocus_AzureSecurityBaselineChecklist.docx",
      "action": "created",
      "success": true,
      "servicenow_sys_id": "e9d8a116477b66103c5e88f4116d438c",
      "error_message": null
    },
    {
      "asset_id": "11537306",
      "asset_name": "LongFocus_Mimecast&SentinelOneConfig.docx",
      "action": "created",
      "success": true,
      "servicenow_sys_id": "0ed8e116477b66103c5e88f4116d4325",
      "error_message": null
    },
    {
      "asset_id": "11538525",
      "asset_name": "LongFocus_GlobalRelayConfig.docx",
      "action": "created",
      "success": true,
      "servicenow_sys_id": "52d8e116477b66103c5e88f4116d4368",
      "error_message": null
    },
    {
      "asset_id": "11538733",
      "asset_name": "LongFocus-TransitionNotes.pptx",
      "action": "created",
      "success": true,
      "servicenow_sys_id": "26d8e116477b66103c5e88f4116d439b",
      "error_message": null
    },
    {
      "asset_id": "11711842",
      "asset_name": "DELETEME - LongFocusTeams-TransitionNotes.pptx",
      "action": "created",
      "success": true,
      "servicenow_sys_id": "4bd82516477b66103c5e88f4116d4314",
      "error_message": null
    },
    {
      "asset_id": "11711844",
      "asset_name": "LongFocusTeams-TransitionNotes.pptx",
      "action": "created",
      "success": true,
      "servicenow_sys_id": "57d82516477b66103c5e88f4116d433f",
      "error_message": null
    },
    {
      "asset_id": "11711845",
      "asset_name": "LongFocus_GlobalRelayTeamsConfig.docx",
      "action": "created",
      "success": true,
      "servicenow_sys_id": "63d82516477b66103c5e88f4116d4365",
      "error_message": null
    },
    {
      "asset_id": "16713139",
      "asset_name": "2024 Long Focus Capital Management Penetration Test Report.pdf",
      "action": "created",
      "success": true,
      "servicenow_sys_id": "3bd82516477b66103c5e88f4116d43cd",
      "error_message": null
    },
    {
      "asset_id": "att_14875253",
      "asset_name": "Microsoft_Cloud_(3).zip",
      "action": "created",
      "success": true,
      "servicenow_sys_id": "0cd86116477b66103c5e88f4116d433a",
      "error_message": null
    },
    {
      "asset_id": "att_10897786",
      "asset_name": "Long_Focus_Capital_-_IKO_Doc-REDACTED.docx",
      "action": "created",
      "success": true,
      "servicenow_sys_id": "f8d8a116477b66103c5e88f4116d4307",
      "error_message": null
    },
    {
      "asset_id": "att_10872898",
      "asset_name": "Long_Focus_Capital_Contacts_20220829.xlsx",
      "action": "created",
      "success": true,
      "servicenow_sys_id": "cdd8a116477b66103c5e88f4116d4330",
      "error_message": null
    },
    {
      "asset_id": "att_10872899",
      "asset_name": "Long_Focus_-_Onboarding_Doc_20220829.docx",
      "action": "created",
      "success": true,
      "servicenow_sys_id": "2dd8a116477b66103c5e88f4116d4386",
      "error_message": null
    },
    {
      "asset_id": "att_11537055",
      "asset_name": "LongFocus_AzureSecurityBaselineChecklist.docx",
      "action": "created",
      "success": true,
      "servicenow_sys_id": "3dd8a116477b66103c5e88f4116d43b9",
      "error_message": null
    },
    {
      "asset_id": "att_11537306",
      "asset_name": "LongFocusMimecastConfig.docx",
      "action": "created",
      "success": true,
      "servicenow_sys_id": "82d8e116477b66103c5e88f4116d4362",
      "error_message": null
    },
    {
      "asset_id": "att_11538525",
      "asset_name": "LongFocus_GlobalRelayConfig.docx",
      "action": "created",
      "success": true,
      "servicenow_sys_id": "26d8e116477b66103c5e88f4116d435e",
      "error_message": null
    },
    {
      "asset_id": "att_11538733",
      "asset_name": "LongFocus-TransitionNotes.pptx",
      "action": "created",
      "success": true,
      "servicenow_sys_id": "bad82516477b66103c5e88f4116d4304",
      "error_message": null
    },
    {
      "asset_id": "att_11711842",
      "asset_name": "LongFocusTeams-TransitionNotes.pptx",
      "action": "created",
      "success": true,
      "servicenow_sys_id": "47d82516477b66103c5e88f4116d4337",
      "error_message": null
    },
    {
      "asset_id": "att_11711844",
      "asset_name": "LongFocusTeams-TransitionNotes.pptx",
      "action": "created",
      "success": true,
      "servicenow_sys_id": "a3d82516477b66103c5e88f4116d435d",
      "error_message": null
    },
    {
      "asset_id": "att_11711845",
      "asset_name": "LongFocus_GlobalRelayTeamsConfig.docx",
      "action": "created",
      "success": true,
      "servicenow_sys_id": "b3d82516477b66103c5e88f4116d43ad",
      "error_message": null
    },
    {
      "asset_id": "att_10839658",
      "asset_name": "RE_Onboarding_Process_-_Long_Focus_Capital.msg",
      "action": "created",
      "success": true,
      "servicenow_sys_id": "aac8edd2477b66103c5e88f4116d43d9",
      "error_message": null
    },
    {
      "asset_id": "att_10839661",
      "asset_name": "RE_Onboarding_Process_-_Long_Focus_Capital.msg",
      "action": "created",
      "success": true,
      "servicenow_sys_id": "36c82116477b66103c5e88f4116d436d",
      "error_message": null
    },
    {
      "asset_id": "att_10839662",
      "asset_name": "RE_Onboarding_Process_-_Long_Focus_Capital.msg",
      "action": "created",
      "success": true,
      "servicenow_sys_id": "17c82116477b66103c5e88f4116d439b",
      "error_message": null
    },
    {
      "asset_id": "att_16713139",
      "asset_name": "2024_Long_Focus_Capital_Management_Penetration_Test_Report.pdf",
      "action": "created",
      "success": true,
      "servicenow_sys_id": "88e82516477b66103c5e88f4116d43da",
      "error_message": null
    }
  ]
}